Workbook

Sheet README
A1: Stress Scenario Package Workbook
A2: Theme: Trump affordability policy signals (credit cards, payments, housing/mortgages, Fed independence)
A3: As of: 2026-01-14 (update inputs & sources as needed)
A5: How to use:
A6: 1) Update the 'Inputs' sheet with your latest baseline market/macro values.
A7: 2) Review the 'Fact_Base' sheet for the policy signal timeline (with sources).
A8: 3) Use 'Shock_Library' to select mild/severe deltas.
A9: 4) 'Paths_12M' provides example 12‑month paths built from the Inputs + deltas.
A10: 5) Map the shocks to your portfolio models (credit, market, liquidity, operational).
A12: Important:
A13: - Numbers in this workbook are scenario assumptions/templates unless explicitly labeled as sourced facts.
A14: - Validate legal/regulatory feasibility with counsel; validate financial impacts with your own analytics.

Sheet Inputs
A1: Variable | B1: Baseline value | C1: Units | D1: Notes / update cadence
A2: Fed funds (midpoint) | B2: 3.625 | C2: % | D2: Template; update from your market data
A3: 10Y U.S. Treasury yield | B3: 4 | C3: % | D3: Template; update daily
A4: 30Y fixed mortgage rate | B4: 6.05 | C4: % | D4: Template; update weekly
A5: Average credit card APR (new accounts) | B5: 23 | C5: % | D5: Template; can differ by product/segment
A6: Unemployment rate | B6: 4.2 | C6: % | D6: Template; update monthly
A7: CPI (YoY) | B7: 2.7 | C7: % | D7: Template; update monthly
A8: Home price growth (YoY) | B8: 2.2 | C8: % | D8: Template; FHFA HPI was ~2.2% YoY through Q3 2025; update with latest release

Sheet Fact_Base
A1: Date | B1: Signal / statement (summary) | C1: Implementation path | D1: Potential exposure mapping | E1: Primary source (URL/text)
A2: 2026-01-07 | B2: Trump said administration is moving to ban large institutional investors from buying single-family homes; asked Congress to codify (steps not specified). | C2: Executive + legislation (unclear) | D2: Housing demand/price; single-family rental (SFR) landlords; homebuilder equities | E2: Reuters: Trump threatens ban on large institutional investors buying single-family homes (Jan 7, 2026)
A3: 2026-01-08 | B3: Trump said he ordered purchase of $200B in mortgage-backed securities via Fannie Mae/Freddie Mac to lower mortgage rates; effect estimated modest (~10–15 bps). | C3: Agency/GSE balance sheet action under FHFA | D3: Mortgage rates, MBS spreads, refi/prepay, originations, MSR, bank IRRBB | E3: Reuters: Trump orders representatives to buy $200B mortgage bonds (Jan 8, 2026)
A4: 2026-01-09 | B4: White House reportedly preparing housing affordability executive order: down payment support via 401(k)/529, investor ban elements, portable/assumable mortgages, etc. Details in flux; partial rollout expected around Davos. | C4: Executive order + potential tax/legislation | D4: Mortgage originations; retirement plan providers; fintech; housing supply policies | E4: Washington Post: draft housing affordability EO (Jan 9, 2026)
A5: 2026-01-10 | B5: Trump called for a one-year 10% cap on credit card interest, starting Jan 20; no implementation details; would likely require Congress. | C5: Legislation required | D5: Card issuer NII; credit access; charge-offs; BNPL substitution; merchant sales | E5: Reuters: banks warn about 10% cap (Jan 12, 2026) / Reuters explainer (Jan 12, 2026)
A6: 2026-01-13 | B6: Trump endorsed Credit Card Competition Act (CCCA) to increase routing competition and reduce swipe fees; would require large banks to offer alternative networks besides Visa/Mastercard. | C6: Legislation | D6: Payments networks; issuer economics; merchant pricing; rewards economics | E6: Bloomberg: Trump targets swipe fees via CCCA (Jan 13, 2026) / PaymentsDive (Jan 13, 2026)
A7: 2026-01-12 to 2026-01-14 | B7: DOJ subpoenas / probe of Fed Chair Powell over HQ renovation; Powell calls it a pretext to influence rate-setting; global central bankers and some U.S. officials warn about Fed independence risks. | C7: Legal/political process; potential appointment risk | D7: Rates volatility; term premium; USD; risk assets; bank ALM and liquidity | E7: Reuters: Powell threatened with indictment / probe sparks pushback (Jan 12–14, 2026)

Sheet Shock_Library
A1: Risk factor | B1: Mild stress delta | C1: Severe stress delta | D1: Units | E1: Notes
A2: Credit card APR (effective) | B2: -10 | C2: -13 | D2: pp | E2: From ~23% to ~13% (mild) or ~10% (severe cap binding)
A3: Card originations / credit line availability | B3: -20 | C3: -40 | D3: % | E3: Issuer tightening; use internal elasticity
A4: Card charge-off rate | B4: 1.5 | C4: 4 | D4: pp | E4: Mix shift + economic slowing; calibrate to your book
A5: Merchant interchange / swipe fee take-rate | B5: -10 | C5: -25 | D5: % | E5: If routing mandates/fee pressure pass-through
A6: 30Y mortgage rate | B6: -0.15 | C6: -0.25 | D6: pp | E6: Near-term effect of $200B MBS purchases; estimates vary
A7: Mortgage refinance application volume | B7: 25 | C7: 60 | D7: % | E7: Refi wave sensitivity; calibrate to rate move
A8: MBS option-adjusted spread (OAS) | B8: -10 | C8: 30 | D8: bp | E8: Compression then widening if volatility rises
A9: 10Y U.S. Treasury yield | B9: 0.5 | C9: 1.5 | D9: pp | E9: Fed-independence/term-premium shock
A10: Credit spreads (IG OAS) | B10: 80 | C10: 200 | D10: bp | E10: Risk-off widening
A11: Equity market level (broad) | B11: -10 | C11: -25 | D11: % | E11: Risk-off selloff
A12: Unemployment rate | B12: 0.7 | C12: 2.5 | D12: pp | E12: Macro slowdown tail
A13: Home prices (national) | B13: -2 | C13: -8 | D13: % | E13: Demand shock tail; region-dependent

Sheet Paths_12M
A1: Month | B1: Baseline Fed funds | C1: Baseline 10Y | D1: Baseline Mortgage 30Y | E1: Baseline Card APR | F1: Scenario 1 Card/Payments (Severe) - Card APR | G1: Scenario 2 Housing (Severe) - Mortgage 30Y | H1: Scenario 3 Fed Independence (Severe) - 10Y | I1: Scenario 3 Fed Independence (Severe) - Mortgage 30Y
A2: M00 | B2: =Inputs!B2 | C2: =Inputs!B3 | D2: =Inputs!B4 | E2: =Inputs!B5 | F2: =IF(ROW()-2<=2, Inputs!B5 + (10-Inputs!B5)*(ROW()-2)/2, 10) | G2: =IF(ROW()-2<=2, Inputs!B4-0.25*(ROW()-2)/2, Inputs!B4-0.25*(1-(ROW()-4)/10)) | H2: =IF(ROW()-2<=1, Inputs!B3+1.5*(ROW()-2), Inputs!B3+1.5-(ROW()-3)*(0.75/11)) | I2: =IF(ROW()-2<=1, Inputs!B4+1.0*(ROW()-2), Inputs!B4+1.0-(ROW()-3)*(0.5/11))
A3: M01 | B3: =Inputs!B2 | C3: =Inputs!B3 | D3: =Inputs!B4 | E3: =Inputs!B5 | F3: =IF(ROW()-2<=2, Inputs!B5 + (10-Inputs!B5)*(ROW()-2)/2, 10) | G3: =IF(ROW()-2<=2, Inputs!B4-0.25*(ROW()-2)/2, Inputs!B4-0.25*(1-(ROW()-4)/10)) | H3: =IF(ROW()-2<=1, Inputs!B3+1.5*(ROW()-2), Inputs!B3+1.5-(ROW()-3)*(0.75/11)) | I3: =IF(ROW()-2<=1, Inputs!B4+1.0*(ROW()-2), Inputs!B4+1.0-(ROW()-3)*(0.5/11))
A4: M02 | B4: =Inputs!B2 | C4: =Inputs!B3 | D4: =Inputs!B4 | E4: =Inputs!B5 | F4: =IF(ROW()-2<=2, Inputs!B5 + (10-Inputs!B5)*(ROW()-2)/2, 10) | G4: =IF(ROW()-2<=2, Inputs!B4-0.25*(ROW()-2)/2, Inputs!B4-0.25*(1-(ROW()-4)/10)) | H4: =IF(ROW()-2<=1, Inputs!B3+1.5*(ROW()-2), Inputs!B3+1.5-(ROW()-3)*(0.75/11)) | I4: =IF(ROW()-2<=1, Inputs!B4+1.0*(ROW()-2), Inputs!B4+1.0-(ROW()-3)*(0.5/11))
A5: M03 | B5: =Inputs!B2 | C5: =Inputs!B3 | D5: =Inputs!B4 | E5: =Inputs!B5 | F5: =IF(ROW()-2<=2, Inputs!B5 + (10-Inputs!B5)*(ROW()-2)/2, 10) | G5: =IF(ROW()-2<=2, Inputs!B4-0.25*(ROW()-2)/2, Inputs!B4-0.25*(1-(ROW()-4)/10)) | H5: =IF(ROW()-2<=1, Inputs!B3+1.5*(ROW()-2), Inputs!B3+1.5-(ROW()-3)*(0.75/11)) | I5: =IF(ROW()-2<=1, Inputs!B4+1.0*(ROW()-2), Inputs!B4+1.0-(ROW()-3)*(0.5/11))
A6: M04 | B6: =Inputs!B2 | C6: =Inputs!B3 | D6: =Inputs!B4 | E6: =Inputs!B5 | F6: =IF(ROW()-2<=2, Inputs!B5 + (10-Inputs!B5)*(ROW()-2)/2, 10) | G6: =IF(ROW()-2<=2, Inputs!B4-0.25*(ROW()-2)/2, Inputs!B4-0.25*(1-(ROW()-4)/10)) | H6: =IF(ROW()-2<=1, Inputs!B3+1.5*(ROW()-2), Inputs!B3+1.5-(ROW()-3)*(0.75/11)) | I6: =IF(ROW()-2<=1, Inputs!B4+1.0*(ROW()-2), Inputs!B4+1.0-(ROW()-3)*(0.5/11))
A7: M05 | B7: =Inputs!B2 | C7: =Inputs!B3 | D7: =Inputs!B4 | E7: =Inputs!B5 | F7: =IF(ROW()-2<=2, Inputs!B5 + (10-Inputs!B5)*(ROW()-2)/2, 10) | G7: =IF(ROW()-2<=2, Inputs!B4-0.25*(ROW()-2)/2, Inputs!B4-0.25*(1-(ROW()-4)/10)) | H7: =IF(ROW()-2<=1, Inputs!B3+1.5*(ROW()-2), Inputs!B3+1.5-(ROW()-3)*(0.75/11)) | I7: =IF(ROW()-2<=1, Inputs!B4+1.0*(ROW()-2), Inputs!B4+1.0-(ROW()-3)*(0.5/11))
A8: M06 | B8: =Inputs!B2 | C8: =Inputs!B3 | D8: =Inputs!B4 | E8: =Inputs!B5 | F8: =IF(ROW()-2<=2, Inputs!B5 + (10-Inputs!B5)*(ROW()-2)/2, 10) | G8: =IF(ROW()-2<=2, Inputs!B4-0.25*(ROW()-2)/2, Inputs!B4-0.25*(1-(ROW()-4)/10)) | H8: =IF(ROW()-2<=1, Inputs!B3+1.5*(ROW()-2), Inputs!B3+1.5-(ROW()-3)*(0.75/11)) | I8: =IF(ROW()-2<=1, Inputs!B4+1.0*(ROW()-2), Inputs!B4+1.0-(ROW()-3)*(0.5/11))
A9: M07 | B9: =Inputs!B2 | C9: =Inputs!B3 | D9: =Inputs!B4 | E9: =Inputs!B5 | F9: =IF(ROW()-2<=2, Inputs!B5 + (10-Inputs!B5)*(ROW()-2)/2, 10) | G9: =IF(ROW()-2<=2, Inputs!B4-0.25*(ROW()-2)/2, Inputs!B4-0.25*(1-(ROW()-4)/10)) | H9: =IF(ROW()-2<=1, Inputs!B3+1.5*(ROW()-2), Inputs!B3+1.5-(ROW()-3)*(0.75/11)) | I9: =IF(ROW()-2<=1, Inputs!B4+1.0*(ROW()-2), Inputs!B4+1.0-(ROW()-3)*(0.5/11))
A10: M08 | B10: =Inputs!B2 | C10: =Inputs!B3 | D10: =Inputs!B4 | E10: =Inputs!B5 | F10: =IF(ROW()-2<=2, Inputs!B5 + (10-Inputs!B5)*(ROW()-2)/2, 10) | G10: =IF(ROW()-2<=2, Inputs!B4-0.25*(ROW()-2)/2, Inputs!B4-0.25*(1-(ROW()-4)/10)) | H10: =IF(ROW()-2<=1, Inputs!B3+1.5*(ROW()-2), Inputs!B3+1.5-(ROW()-3)*(0.75/11)) | I10: =IF(ROW()-2<=1, Inputs!B4+1.0*(ROW()-2), Inputs!B4+1.0-(ROW()-3)*(0.5/11))
A11: M09 | B11: =Inputs!B2 | C11: =Inputs!B3 | D11: =Inputs!B4 | E11: =Inputs!B5 | F11: =IF(ROW()-2<=2, Inputs!B5 + (10-Inputs!B5)*(ROW()-2)/2, 10) | G11: =IF(ROW()-2<=2, Inputs!B4-0.25*(ROW()-2)/2, Inputs!B4-0.25*(1-(ROW()-4)/10)) | H11: =IF(ROW()-2<=1, Inputs!B3+1.5*(ROW()-2), Inputs!B3+1.5-(ROW()-3)*(0.75/11)) | I11: =IF(ROW()-2<=1, Inputs!B4+1.0*(ROW()-2), Inputs!B4+1.0-(ROW()-3)*(0.5/11))
A12: M10 | B12: =Inputs!B2 | C12: =Inputs!B3 | D12: =Inputs!B4 | E12: =Inputs!B5 | F12: =IF(ROW()-2<=2, Inputs!B5 + (10-Inputs!B5)*(ROW()-2)/2, 10) | G12: =IF(ROW()-2<=2, Inputs!B4-0.25*(ROW()-2)/2, Inputs!B4-0.25*(1-(ROW()-4)/10)) | H12: =IF(ROW()-2<=1, Inputs!B3+1.5*(ROW()-2), Inputs!B3+1.5-(ROW()-3)*(0.75/11)) | I12: =IF(ROW()-2<=1, Inputs!B4+1.0*(ROW()-2), Inputs!B4+1.0-(ROW()-3)*(0.5/11))
A13: M11 | B13: =Inputs!B2 | C13: =Inputs!B3 | D13: =Inputs!B4 | E13: =Inputs!B5 | F13: =IF(ROW()-2<=2, Inputs!B5 + (10-Inputs!B5)*(ROW()-2)/2, 10) | G13: =IF(ROW()-2<=2, Inputs!B4-0.25*(ROW()-2)/2, Inputs!B4-0.25*(1-(ROW()-4)/10)) | H13: =IF(ROW()-2<=1, Inputs!B3+1.5*(ROW()-2), Inputs!B3+1.5-(ROW()-3)*(0.75/11)) | I13: =IF(ROW()-2<=1, Inputs!B4+1.0*(ROW()-2), Inputs!B4+1.0-(ROW()-3)*(0.5/11))
A14: M12 | B14: =Inputs!B2 | C14: =Inputs!B3 | D14: =Inputs!B4 | E14: =Inputs!B5 | F14: =IF(ROW()-2<=2, Inputs!B5 + (10-Inputs!B5)*(ROW()-2)/2, 10) | G14: =IF(ROW()-2<=2, Inputs!B4-0.25*(ROW()-2)/2, Inputs!B4-0.25*(1-(ROW()-4)/10)) | H14: =IF(ROW()-2<=1, Inputs!B3+1.5*(ROW()-2), Inputs!B3+1.5-(ROW()-3)*(0.75/11)) | I14: =IF(ROW()-2<=1, Inputs!B4+1.0*(ROW()-2), Inputs!B4+1.0-(ROW()-3)*(0.5/11))

Sheet Sources
A1: Topic | B1: Source | C1: Date | D1: Notes
A2: Credit card APR cap (10%) | B2: Reuters – Banks warn consumers will be hurt by Trump's 10% cap on credit card interest rates | C2: 2026-01-12 | D2: Cap proposed for 1 year starting Jan 20; banks cite credit access impact; contains CFPB APR data
A3: Credit card rate cap explainer | B3: Reuters – Explainer on how cap could reshape consumer lending | C3: 2026-01-12 | D3: Includes Bankrate average APR and Fed credit card balance figure
A4: Swipe fee / routing policy | B4: Bloomberg – Trump targets card swipe fees via Credit Card Competition Act | C4: 2026-01-13 | D4: Endorses CCCA; aims to bypass Visa/Mastercard for large issuers
A5: CCCA details | B5: PaymentsDive – Trump endorses Credit Card Competition Act | C5: 2026-01-13 | D5: Applies to issuers with $100B+ assets; routing competition
A6: MBS purchases | B6: Reuters – Trump orders $200B mortgage bond buys | C6: 2026-01-08 | D6: Via Fannie/Freddie; estimated 10–15bp mortgage-rate impact
A7: Investor ban | B7: Reuters – Trump threatens ban on institutional investors buying single-family homes | C7: 2026-01-07 | D7: Requests Congress to codify; market reaction
A8: Housing EO drafting | B8: Washington Post – Draft housing affordability executive order | C8: 2026-01-09 | D8: Down payment support via 401(k)/529; investor ban; portable/assumable mortgages; details in flux
A9: Fed independence probe | B9: Reuters – Powell says administration threatened indictment; probe sparks pushback | C9: 2026-01-12/13 | D9: Subpoenas; Powell says pretext; market implications
A10: Fed independence reactions | B10: Reuters – Rehn warns erosion of Fed independence raises inflation; Goolsbee defends Powell | C10: 2026-01-14 | D10: Global central bank support; risks to stability
